flask_llm_renderer/__init__.py
flask_llm_renderer/core.py
flask_llm_renderer/templates/viewer.html
flask_llm_renderer-0.1.0.dist-info/METADATA
flask_llm_renderer-0.1.0.dist-info/WHEEL
flask_llm_renderer-0.1.0.dist-info/top_level.txt
flask_llm_renderer-0.1.0.dist-info/RECORD
