Metadata-Version: 2.4
Name: flask_llm_renderer
Version: 0.1.0
Summary: A Flask extension to render HTML dashboards with LLMs
Home-page: https://github.com/ismaeelbashir03/flask-llm-renderer
Author: Ismaeel Bashir
Author-email: ismaeelbashir2003@gmail.com
Classifier: Development Status :: 3 - Alpha
Classifier: Intended Audience :: Developers
Classifier: License :: OSI Approved :: MIT License
Classifier: Programming Language :: Python :: 3
Classifier: Programming Language :: Python :: 3.7
Classifier: Programming Language :: Python :: 3.8
Classifier: Programming Language :: Python :: 3.9
Classifier: Framework :: Flask
Requires-Python: >=3.7
Requires-Dist: Flask
Requires-Dist: Flask-SocketIO
Requires-Dist: openai
Requires-Dist: anthropic
Requires-Dist: eventlet
Dynamic: author
Dynamic: author-email
Dynamic: classifier
Dynamic: description
Dynamic: description-content-type
Dynamic: home-page
Dynamic: requires-dist
Dynamic: requires-python
Dynamic: summary
